{
  "bookingId": "1SXXX1A2B3C4D",
  "startDate": "2024-07-09",
  "endDate": "2024-07-19",
  "isCancelable": false,
  "isTicketed": false,
  "agencyCustomerNumber": "1234567",
  "creationDetails": {
    "creationUserSine": "A12",
    "creationDate": "2024-01-09",
    "creationTime": "15:00",
    "purchaseDeadlineDate": "2024-01-09",
    "purchaseDeadlineTime": "15:00",
    "agencyIataNumber": "99119911",
    "userWorkPcc": "AB12",
    "userHomePcc": "CD34",
    "primeHostId": "1S"
  },
  "contactInfo": {
    "emails": ["travel@sabre.com"],
    "phones": ["+1-555-123-4567"]
  },
  "travelers": [
    {
      "givenName": "John",
      "middleName": "W",
      "surname": "Smith",
      "birthDate": "2024-01-23",
      "gender": "FEMALE",
      "type": "ADULT",
      "passengerCode": "ADT",
      "nameAssociationId": "3",
      "nameReferenceCode": "C05",
      "isGrouped": true,
      "emails": ["john@smith.family.priv"],
      "phones": [
        {
          "number": "+1-555-123-4567",
          "label": "M"
        }
      ],
      "remarks": [
        {
          "type": "GENERAL",
          "alphaCode": "T",
          "text": "XXATW/"
        }
      ],
      "address": {
        "street": "1230 Ellen Ave, apt 10",
        "city": "Dallas",
        "stateProvince": "TX",
        "postalCode": "75063",
        "countryCode": "US",
        "name": "John Smith",
        "freeText": "John Smith\n1230 Ellen Ave, Apt 10\nDallas, TX 75063\nUS\n"
      },
      "identityDocuments": [
        {
          "documentNumber": "0123456789",
          "documentType": "PASSPORT",
          "documentSubType": "RUC",
          "expiryDate": "2024-07-09",
          "issuingCountryCode": "US",
          "residenceCountryCode": "US",
          "placeOfIssue": "ROME",
          "placeOfBirth": "KOSZALIN",
          "hostCountryCode": "US",
          "issueDate": "2024-07-09",
          "givenName": "John",
          "middleName": "Jack",
          "surname": "Smith",
          "birthDate": "2024-12-02",
          "gender": "FEMALE",
          "isPrimaryDocumentHolder": true,
          "isLapChildDocument": true,
          "residenceDestinationAddress": {
            "street": "1230 Ellen Ave, apt 10",
            "city": "Dallas",
            "stateProvince": "TX",
            "postalCode": "75063",
            "countryCode": "US"
          },
          "flightIndices": [1],
          "itemId": "76c2817b178cc264fa44cf85df1da5fb9e1b963006b2339aa5edc09129415bba5fcf5bf91a5f",
          "citizenshipCountryCode": "US"
        }
      ],
      "loyaltyPrograms": [
        {
          "supplierCode": "AA",
          "programType": "FREQUENT_FLYER",
          "programNumber": "987654321",
          "tierLevel": 3,
          "receiverCode": "UA"
        }
      ],
      "ancillaries": [
        {
          "itemId": "12",
          "commercialName": "UPTO33LB 15KG BAGGAGE",
          "numberOfItems": 1,
          "reasonForIssuanceCode": "C",
          "reasonForIssuanceName": "BAGGAGE",
          "subcode": "05Z",
          "airlineCode": "EY",
          "vendorCode": "EY",
          "source": "ATPCO",
          "electronicMiscellaneousDocumentNumber": "6074333222111",
          "isRefundable": true,
          "isCommissionable": false,
          "flightApplicabilityType": "Single",
          "flights": [
            {
              "itemId": "12"
            }
          ],
          "statusCode": "HD",
          "statusName": "Confirmed",
          "totals": {
            "subtotal": "100.00",
            "taxes": "8.00",
            "total": "128.00",
            "currencyCode": "USD",
            "fees": "20.00",
            "netRemit": "110.00"
          },
          "taxes": [
            {
              "taxCode": "XY",
              "amount": "100.00"
            }
          ]
        }
      ],
      "formOfPaymentIndices": [1],
      "employerIndex": 1
    }
  ],
  "travelersGroup": {
    "itemId": "3",
    "name": "GROUP ONE",
    "numberOfTravelers": 1,
    "numberOfTravelersRemaining": 1
  },
  "flights": [
    {
      "itemId": "12",
      "confirmationId": "NIEBNY",
      "sourceType": "NDC",
      "flightNumber": 123,
      "airlineCode": "AA",
      "airlineName": "AMERICAN AIRLINES",
      "operatingFlightNumber": 321,
      "operatingAirlineCode": "UA",
      "operatingAirlineName": "UNITED AIRLINES",
      "fromAirportCode": "DFW",
      "toAirportCode": "HNL",
      "departureDate": "2024-07-09",
      "departureTime": "09:15",
      "updatedDepartureDate": "2024-07-09",
      "updatedDepartureTime": "09:25",
      "departureTerminalName": "Terminal D",
      "departureGate": "D",
      "arrivalDate": "2024-07-09",
      "arrivalTime": "12:28",
      "updatedArrivalDate": "2024-07-09",
      "updatedArrivalTime": "12:38",
      "arrivalTerminalName": "Terminal 1",
      "arrivalGate": "1",
      "seats": [
        {
          "number": "13A",
          "characteristics": ["K"],
          "statusCode": "AF",
          "statusName": "Confirmed"
        }
      ],
      "changeOfGaugeSeats": [
        {
          "number": "13A",
          "characteristics": ["K"],
          "statusCode": "AF",
          "statusName": "Confirmed"
        }
      ],
      "numberOfSeats": 1,
      "cabinTypeName": "Coach",
      "cabinTypeCode": "C",
      "aircraftTypeCode": "E90",
      "aircraftTypeName": "EMBRAER EMB E90",
      "bookingClass": "Y",
      "meals": [
        {
          "code": "H",
          "description": "Hot meal"
        }
      ],
      "flightStatusCode": "AF",
      "flightStatusName": "Confirmed",
      "durationInMinutes": 590,
      "distanceInMiles": 5143,
      "hiddenStopAircraftTypeCode": "E90",
      "hiddenStopAircraftTypeName": "EMBRAER EMB E90",
      "hiddenStopAirportCode": "HAV",
      "hiddenStopArrivalDate": "2024-07-09",
      "hiddenStopArrivalTime": "09:15",
      "hiddenStopDepartureDate": "2024-07-09",
      "hiddenStopDepartureTime": "09:15",
      "hiddenStops": [
        {
          "airportCode": "DFW",
          "departureDate": "2024-07-09",
          "departureTime": "09:15",
          "arrivalDate": "2024-07-09",
          "arrivalTime": "12:28",
          "aircraftTypeCode": "E90",
          "aircraftTypeName": "EMBRAER EMB E90",
          "durationInMinutes": 300
        }
      ],
      "travelerIndices": [1],
      "identityDocuments": [
        {
          "itemId": "76c2817b178cc264fa44cf85df1da5fb9e1b963006b2339aa5edc09129415bba5fcf5bf91a5f",
          "status": "Confirmed"
        }
      ],
      "isPast": false
    }
  ],
  "journeys": [
    {
      "firstAirportCode": "DFW",
      "departureDate": "2024-07-09",
      "departureTime": "09:15",
      "lastAirportCode": "HNL",
      "numberOfFlights": 1
    }
  ],
  "fareRules": [
    {
      "originAirportCode": "DFW",
      "destinationAirportCode": "ATL",
      "owningAirlineCode": "AA",
      "passengerCode": "ADT",
      "isRefundable": true,
      "refundPenalties": [
        {
          "applicability": "BEFORE_DEPARTURE",
          "conditionsApply": false,
          "penalty": {
            "amount": "100.00",
            "currencyCode": "USD"
          },
          "hasNoShowCost": true,
          "noShowPenalty": {
            "amount": "100.00",
            "currencyCode": "USD"
          }
        }
      ],
      "isChangeable": true,
      "exchangePenalties": [
        {
          "applicability": "BEFORE_DEPARTURE",
          "conditionsApply": false,
          "penalty": {
            "amount": "100.00",
            "currencyCode": "USD"
          },
          "hasNoShowCost": true,
          "noShowPenalty": {
            "amount": "100.00",
            "currencyCode": "USD"
          }
        }
      ],
      "isCancelable": true,
      "cancelPenalties": [
        {
          "applicability": "BEFORE_DEPARTURE",
          "conditionsApply": false,
          "penalty": {
            "amount": "100.00",
            "currencyCode": "USD"
          },
          "hasNoShowCost": true,
          "noShowPenalty": {
            "amount": "100.00",
            "currencyCode": "USD"
          }
        }
      ]
    }
  ],
  "fareOffers": [
    {
      "travelerIndices": [1],
      "flights": [
        {
          "itemId": "12"
        }
      ],
      "cabinBaggageAllowance": {
        "maximumPieces": 1,
        "totalWeightInPounds": 50,
        "totalWeightInKilograms": 23,
        "baggagePieces": [
          {
            "maximumSizeInInches": 46,
            "maximumSizeInCentimeters": 118,
            "maximumWeightInPounds": 50,
            "maximumWeightInKilograms": 23,
            "numberOfPieces": 1,
            "specialItemDescription": "SKI EQUIPMENT",
            "isCheckInOnly": true,
            "fee": {
              "amount": "100.00",
              "currencyCode": "USD"
            }
          }
        ]
      },
      "checkedBaggageAllowance": {
        "maximumPieces": 1,
        "totalWeightInPounds": 50,
        "totalWeightInKilograms": 23,
        "baggagePieces": [
          {
            "maximumSizeInInches": 46,
            "maximumSizeInCentimeters": 118,
            "maximumWeightInPounds": 50,
            "maximumWeightInKilograms": 23,
            "numberOfPieces": 1,
            "specialItemDescription": "SKI EQUIPMENT",
            "isCheckInOnly": true,
            "fee": {
              "amount": "100.00",
              "currencyCode": "USD"
            }
          }
        ]
      },
      "cabinBaggageCharges": [
        {
          "maximumSizeInInches": 46,
          "maximumSizeInCentimeters": 118,
          "maximumWeightInPounds": 50,
          "maximumWeightInKilograms": 23,
          "numberOfPieces": 1,
          "specialItemDescription": "SKI EQUIPMENT",
          "isCheckInOnly": true,
          "fee": {
            "amount": "100.00",
            "currencyCode": "USD"
          }
        }
      ],
      "checkedBaggageCharges": [
        {
          "maximumSizeInInches": 46,
          "maximumSizeInCentimeters": 118,
          "maximumWeightInPounds": 50,
          "maximumWeightInKilograms": 23,
          "numberOfPieces": 1,
          "specialItemDescription": "SKI EQUIPMENT",
          "isCheckInOnly": true,
          "fee": {
            "amount": "100.00",
            "currencyCode": "USD"
          }
        }
      ]
    }
  ],
  "fares": [
    {
      "creationDetails": {
        "creationUserSine": "A12",
        "creationDate": "2024-01-09",
        "creationTime": "15:00",
        "purchaseDeadlineDate": "2024-01-09",
        "purchaseDeadlineTime": "15:00",
        "agencyIataNumber": "99119911",
        "userWorkPcc": "AB12",
        "userHomePcc": "CD34",
        "primeHostId": "1S"
      },
      "airlineCode": "AA",
      "fareCalculationLine": "BUE AA DFW Q430.00 5740.00NUC6170.00END ROE1.00 XT175.50TQ175.50QO315.90US96.50YC122.90XY69.50XA",
      "tourCode": "123456789ABCDE",
      "isNegotiatedFare": true,
      "travelerIndices": [1],
      "commission": {
        "commissionAmount": "25.00",
        "currencyCode": "USD",
        "commissionPercentage": "5.00"
      },
      "fareConstruction": [
        {
          "flights": [
            {
              "itemId": "12"
            }
          ],
          "flightIndices": [1],
          "fareBasisCode": "ABCDE10",
          "baseRate": {
            "amount": "100.00",
            "currencyCode": "USD"
          },
          "brandFareCode": "ECOFLEX",
          "brandFareName": "ECO FLEX",
          "brandProgramCode": "CFFLH",
          "brandProgramName": "LH BRANDED FARES INTERCONT",
          "brandAttributes": [
            {
              "itemId": "SABRE_NDCC_ID_1",
              "description": "Qantas Points"
            }
          ],
          "isCurrentItinerary": false,
          "checkedBaggageAllowance": {
            "maximumPieces": 1,
            "totalWeightInPounds": 50,
            "totalWeightInKilograms": 23,
            "baggagePieces": [
              {
                "maximumSizeInInches": 46,
                "maximumSizeInCentimeters": 118,
                "maximumWeightInPounds": 50,
                "maximumWeightInKilograms": 23,
                "numberOfPieces": 1,
                "specialItemDescription": "SKI EQUIPMENT",
                "isCheckInOnly": true,
                "fee": {
                  "amount": "100.00",
                  "currencyCode": "USD"
                }
              }
            ]
          }
        }
      ],
      "taxBreakdown": [
        {
          "taxCode": "XY",
          "taxAmount": {
            "amount": "100.00",
            "currencyCode": "USD"
          }
        }
      ],
      "totals": {
        "subtotal": "100.00",
        "taxes": "8.00",
        "total": "128.00",
        "currencyCode": "USD",
        "fees": "20.00",
        "netRemit": "110.00"
      },
      "bundledServicesAndFees": [
        {
          "type": "FEE",
          "code": "SEAT",
          "quantity": 1,
          "amount": "100.00",
          "currencyCode": "USD",
          "description": "Qantas Points"
        }
      ],
      "pricingTypeCode": "S",
      "pricingTypeName": "Manual",
      "pricingStatusCode": "A",
      "pricingStatusName": "Active",
      "hasValidPricing": false,
      "initialSellingFare": {
        "totals": {
          "subtotal": "100.00",
          "taxes": "8.00",
          "total": "128.00",
          "currencyCode": "USD"
        },
        "fareDifferenceBreakdown": {
          "adjustedAmount": "100.00",
          "currencyCode": "USD",
          "goodsAndServicesTaxes": [
            {
              "code": "D",
              "amount": "5.00",
              "percentage": "5.00"
            }
          ],
          "fees": [
            {
              "code": "D",
              "type": "PTK",
              "amount": "25.00"
            }
          ]
        }
      },
      "requestedTravelerType": "C08",
      "pricedTravelerType": "C08",
      "recordTypeCode": "PQ",
      "recordTypeName": "Price Quote",
      "recordId": "12"
    }
  ],
  "remarks": [
    {
      "type": "GENERAL",
      "alphaCode": "T",
      "text": "XXATW/"
    }
  ],
  "allSegments": [
    {
      "id": "12",
      "type": "FLIGHT",
      "text": "123",
      "vendorCode": "AA",
      "date": "2024-07-09",
      "time": "09:15",
      "locationCode": "ATL",
      "address": {
        "street": "1230 Ellen Ave, apt 10",
        "city": "Dallas",
        "stateProvince": "TX",
        "postalCode": "75063",
        "countryCode": "US",
        "name": "John Smith",
        "freeText": "John Smith\n1230 Ellen Ave, Apt 10\nDallas, TX 75063\nUS\n"
      },
      "startDate": "2024-07-09",
      "startTime": "09:15",
      "startLocationCode": "DFW",
      "startAddress": {
        "street": "1230 Ellen Ave, apt 10",
        "city": "Dallas",
        "stateProvince": "TX",
        "postalCode": "75063",
        "countryCode": "US",
        "name": "John Smith",
        "freeText": "John Smith\n1230 Ellen Ave, Apt 10\nDallas, TX 75063\nUS\n"
      },
      "endDate": "2024-07-09",
      "endTime": "12:28",
      "endLocationCode": "HNL",
      "endAddress": {
        "street": "1230 Ellen Ave, apt 10",
        "city": "Dallas",
        "stateProvince": "TX",
        "postalCode": "75063",
        "countryCode": "US",
        "name": "John Smith",
        "freeText": "John Smith\n1230 Ellen Ave, Apt 10\nDallas, TX 75063\nUS\n"
      }
    }
  ],
  "flightTickets": [
    {
      "number": "0167489825830",
      "date": "2024-07-01",
      "agencyIataNumber": "12344321",
      "airlineCode": "AA",
      "travelerIndex": 1,
      "flightCoupons": [
        {
          "itemId": "12",
          "couponStatus": "Printed",
          "couponStatusCode": "PR"
        }
      ],
      "allCoupons": [
        {
          "couponStatus": "Printed",
          "couponStatusCode": "PR",
          "itemId": "12"
        }
      ],
      "payment": {
        "subtotal": "100.00",
        "taxes": "8.00",
        "total": "128.00",
        "currencyCode": "USD",
        "fees": "20.00",
        "netRemit": "110.00"
      },
      "isBundledTicket": true,
      "ticketStatusName": "Issued",
      "ticketStatusCode": "TE",
      "ticketingPcc": "G7HE",
      "commission": {
        "commissionAmount": "25.00",
        "currencyCode": "USD",
        "commissionPercentage": "5.00"
      }
    }
  ],
  "payments": {
    "flightTotals": [
      {
        "subtotal": "100.00",
        "taxes": "8.00",
        "total": "128.00",
        "currencyCode": "USD",
        "fees": "20.00",
        "netRemit": "110.00"
      }
    ],
    "flightCurrentTotals": [
      {
        "subtotal": "100.00",
        "taxes": "8.00",
        "total": "128.00",
        "currencyCode": "USD",
        "fees": "20.00",
        "netRemit": "110.00"
      }
    ],
    "hotelTotals": [
      {
        "subtotal": "100.00",
        "taxes": "8.00",
        "total": "128.00",
        "currencyCode": "USD",
        "fees": "20.00",
        "netRemit": "110.00"
      }
    ],
    "carTotals": [
      {
        "subtotal": "100.00",
        "taxes": "8.00",
        "total": "128.00",
        "currencyCode": "USD",
        "fees": "20.00",
        "netRemit": "110.00"
      }
    ],
    "trainTotals": [
      {
        "subtotal": "100.00",
        "taxes": "8.00",
        "total": "128.00",
        "currencyCode": "USD",
        "fees": "20.00",
        "netRemit": "110.00"
      }
    ],
    "formsOfPayment": [
      {
        "cardTypeCode": "VI",
        "cardNumber": "4537156488578956",
        "cardSecurityCode": "123",
        "expiryDate": "2024-07",
        "extendedPayment": 12,
        "miscellaneousCreditCode": "PL189947",
        "numberOfInstallments": 4,
        "airlinePlanCode": "RG065",
        "installmentAmount": "100",
        "type": "CHECK",
        "cardHolder": {
          "givenName": "John",
          "surname": "Smith",
          "email": "john@smith.family.priv",
          "phone": "+1-555-123-4567",
          "address": {
            "street": "1230 Ellen Ave, apt 10",
            "city": "Dallas",
            "stateProvince": "TX",
            "postalCode": "75063",
            "countryCode": "US"
          }
        },
        "manualApproval": {
          "code": "12345",
          "requestDateTime": "2024-07-09T09:15:00Z",
          "expiryDateTime": "2024-07-09T09:15:00Z",
          "airlineCode": "AA",
          "amount": "100.00",
          "currencyCode": "USD"
        },
        "authentications": [
          {
            "secureAuthenticationValue": "ABC123455533533444455555678",
            "secureTransactionId": "ABCDEFGHI123456789012!.1234567890123",
            "issueCode": "AO",
            "resultCode": "OK",
            "cardNumberCollectionCode": "K",
            "channelCode": "MO",
            "electronicCommerceIndicator": "12",
            "exemptionTypeCode": "SC",
            "updatedDateTime": "2024-07-07T16:00:00Z",
            "mandateTypeCode": "NA",
            "merchantName": "TEST CREDIT CARD",
            "originalPaymentReference": "1234547839012345",
            "amount": "1234.56",
            "currencyCode": "USD",
            "tokenAuthenticationValue": "ABC3434334343556677487312567",
            "verificationResultCode": "PASS",
            "version": "120"
          }
        ],
        "virtualCard": {
          "customerAccountCode": "John",
          "agencyEmail": "john@smith.family.priv",
          "hotelFax": "+1-555-123-4567",
          "hotelName": "Ilia Hotel and Luxury Suites",
          "roomType": "2 double beds",
          "roomDescription": "Deluxe Room, 2 Double Beds",
          "rateAmount": {
            "amount": "100.00",
            "currencyCode": "USD"
          },
          "virtualCardCharges": ["Breakfast"]
        },
        "agencyIataNumber": "129345738",
        "agencyAddress": {
          "street": "1230 Ellen Ave, apt 10",
          "city": "Dallas",
          "stateProvince": "TX",
          "postalCode": "75063",
          "countryCode": "US",
          "name": "John Smith",
          "freeText": "John Smith\n1230 Ellen Ave, Apt 10\nDallas, TX 75063\nUS\n"
        },
        "corporateId": "CC006",
        "companyAddress": {
          "street": "1230 Ellen Ave, apt 10",
          "city": "Dallas",
          "stateProvince": "TX",
          "postalCode": "75063",
          "countryCode": "US",
          "name": "John Smith",
          "freeText": "John Smith\n1230 Ellen Ave, Apt 10\nDallas, TX 75063\nUS\n"
        },
        "voucher": {
          "billingNumber": "1234567",
          "type": "FC"
        },
        "netBalance": "300.20",
        "docketPrefix": "AGT*V",
        "docketNumber": "654456",
        "docketIssuingAgentInitials": "LS",
        "docketDescription": "DOCKET NUM 0123456",
        "governmentTravelRequestDescription": "REQ-123456",
        "invoiceDescription": "AGT INVOICE",
        "useType": "Unknown",
        "tripType": "Unknown",
        "useTypes": ["Unknown"],
        "tripTypes": ["Unknown"],
        "isAgencyPaymentCard": false,
        "addInvoiceDescriptionPrefix": false
      }
    ],
    "ancillaryTotals": [
      {
        "subtotal": "100.00",
        "taxes": "8.00",
        "total": "128.00",
        "currencyCode": "USD"
      }
    ]
  },
  "otherServices": [
    {
      "airlineCode": "AA",
      "travelerIndex": 1,
      "serviceMessage": "/CX-J674A0957C0",
      "chainCode": "BY",
      "vendorCode": "ZE"
    }
  ],
  "futureTicketingPolicy": {
    "ticketingPcc": "G7RE",
    "queueNumber": "55",
    "ticketingDate": "2024-07-09",
    "ticketingTime": "11:00",
    "comment": "TICKET BEFORE TUES"
  },
  "specialServices": [
    {
      "travelerIndices": [1],
      "flights": [
        {
          "itemId": "12"
        }
      ],
      "code": "WCHR",
      "name": "Wheelchair/Passenger can walk up stairs",
      "message": "/PREPAID",
      "statusCode": "HK",
      "statusName": "Confirmed"
    }
  ],
  "retentionEndDate": "2024-01-30",
  "retentionLabel": "RETENTION DATE",
  "accountingItems": [
    {
      "fareApplicationType": "Single Traveler",
      "formOfPaymentType": "Cash",
      "creationType": "Exchange",
      "airlineCode": "AA",
      "ticketNumber": "2200011234567",
      "commission": {
        "commissionAmount": "25.00",
        "currencyCode": "USD",
        "commissionPercentage": "5.00"
      },
      "fareAmount": "520.00",
      "taxAmount": "123.00",
      "travelerIndices": [1],
      "tariffBasisType": "Foreign",
      "cardNumber": "4537156488578956",
      "cardTypeCode": "VI",
      "currencyCode": "USD",
      "goodsAndServicesTax": {
        "code": "D",
        "amount": "5.00",
        "percentage": "5.00"
      }
    }
  ],
  "nonElectronicTickets": [
    {
      "ticketStatus": "Active",
      "ticketNumber": "0011234567899",
      "travelerIndex": 1,
      "ticketingUserCode": "A12",
      "ticketingPcc": "G7HE",
      "date": "2024-07-01",
      "time": "09:15"
    }
  ],
  "travelersEmployers": [
    {
      "idType": "GST",
      "employerId": "22AAAAA0000A1Z5",
      "employerName": "Sabre",
      "phones": [
        {
          "number": "+1-555-123-4567",
          "label": "M"
        }
      ],
      "emails": ["john@gst.company.com"],
      "street": "1230 Ellen Ave, apt 10",
      "city": "Dallas",
      "stateProvince": "TX",
      "postalCode": "75063",
      "countryCode": "US"
    }
  ],
  "timestamp": "2024-10-28T11:11:21Z",
  "bookingSignature": "76c2817b178cc264fa44cf85df1da5fb9e1b963006b2339aa5edc09129415bba5fcf5bf91a5f",
  "request": {
    "confirmationId": "GLEBNY",
    "bookingSource": "SABRE",
    "targetPcc": "G7HE",
    "givenName": "John",
    "middleName": "W",
    "surname": "Smith",
    "returnOnly": ["FLIGHTS"],
    "extraFeatures": {
      "returnFrequentRenter": false,
      "returnWalletFormsOfPayment": false,
      "returnFiscalId": false,
      "returnEmptySeatObjects": true
    },
    "unmaskPaymentCardNumbers": false
  },
  "errors": [
    {
      "category": "BAD_REQUEST",
      "type": "REQUIRED_FIELD_MISSING",
      "description": "may not be null",
      "fieldPath": "someObject.someFieldName",
      "fieldName": "someName",
      "fieldValue": "field value"
    }
  ]
}
